odoo/addons/web_widget_text_markdown/README.rst
odoo/addons/web_widget_text_markdown/__init__.py
odoo/addons/web_widget_text_markdown/__manifest__.py
odoo/addons/web_widget_text_markdown/demo/bootstrap_markdown.xml
odoo/addons/web_widget_text_markdown/i18n/web_widget_text_markdown.pot
odoo/addons/web_widget_text_markdown/readme/CONTRIBUTORS.rst
odoo/addons/web_widget_text_markdown/readme/CREDITS.rst
odoo/addons/web_widget_text_markdown/readme/DESCRIPTION.rst
odoo/addons/web_widget_text_markdown/readme/ROADMAP.rst
odoo/addons/web_widget_text_markdown/readme/USAGE.rst
odoo/addons/web_widget_text_markdown/static/description/icon.png
odoo/addons/web_widget_text_markdown/static/description/index.html
odoo/addons/web_widget_text_markdown/static/src/css/web_widget_text_markdown.css
odoo/addons/web_widget_text_markdown/static/src/js/web_widget_text_markdown.js
odoo/addons/web_widget_text_markdown/static/src/lib/bootstrap-markdown.js
odoo/addons/web_widget_text_markdown/static/src/lib/bootstrap-markdown.min.css
odoo/addons/web_widget_text_markdown/static/src/lib/marked.js
odoo/addons/web_widget_text_markdown/static/src/lib/showdown-footnotes.js
odoo/addons/web_widget_text_markdown/static/src/lib/showdown-table.js
odoo/addons/web_widget_text_markdown/static/src/lib/showdown-toc.js
odoo/addons/web_widget_text_markdown/static/src/lib/showdown.js
odoo/addons/web_widget_text_markdown/static/tests/js/web_widget_text_markdown.js
odoo_addon_web_widget_text_markdown-15.0.1.0.0.1.dist-info/METADATA
odoo_addon_web_widget_text_markdown-15.0.1.0.0.1.dist-info/WHEEL
odoo_addon_web_widget_text_markdown-15.0.1.0.0.1.dist-info/top_level.txt
odoo_addon_web_widget_text_markdown-15.0.1.0.0.1.dist-info/RECORD
