Metadata-Version: 2.1
Name: odoo-addon-web_widget_text_markdown
Version: 15.0.1.0.0.1
Summary: Widget to text fields that adds markdown support
Home-page: https://github.com/OCA/web
Author: Alexandre Díaz, Komit, Sudokeys, Sunflower IT, Odoo Community Association (OCA)
Author-email: support@odoo-community.org
License: AGPL-3
Classifier: Programming Language :: Python
Classifier: Framework :: Odoo
Classifier: Framework :: Odoo :: 15.0
Classifier: License :: OSI Approved :: GNU Affero General Public License v3
Requires-Python: >=3.8
Requires-Dist: odoo <15.1dev,>=15.0a
